hvl_ccb/__init__.py
hvl_ccb/configuration.py
hvl_ccb/error.py
hvl_ccb/experiment_manager.py
hvl_ccb/py.typed
hvl_ccb/_dev/__init__.py
hvl_ccb/_dev/labjack.py
hvl_ccb/comm/__init__.py
hvl_ccb/comm/base.py
hvl_ccb/comm/labjack_ljm.py
hvl_ccb/comm/modbus_tcp.py
hvl_ccb/comm/opc.py
hvl_ccb/comm/serial.py
hvl_ccb/comm/tcp.py
hvl_ccb/comm/visa.py
hvl_ccb/dev/__init__.py
hvl_ccb/dev/base.py
hvl_ccb/dev/utils.py
hvl_ccb/dev/visa.py
hvl_ccb/dev/crylas/__init__.py
hvl_ccb/dev/crylas/crylas.py
hvl_ccb/dev/cube/__init__.py
hvl_ccb/dev/cube/advanced.py
hvl_ccb/dev/cube/alarms.py
hvl_ccb/dev/cube/base.py
hvl_ccb/dev/cube/constants.py
hvl_ccb/dev/cube/earthing_stick.py
hvl_ccb/dev/cube/errors.py
hvl_ccb/dev/cube/picube.py
hvl_ccb/dev/cube/support.py
hvl_ccb/dev/cube/switches.py
hvl_ccb/dev/ea_psi9000/__init__.py
hvl_ccb/dev/ea_psi9000/ea_psi9000.py
hvl_ccb/dev/fluke884x/__init__.py
hvl_ccb/dev/fluke884x/base.py
hvl_ccb/dev/fluke884x/constants.py
hvl_ccb/dev/fluke884x/ranges.py
hvl_ccb/dev/fug/__init__.py
hvl_ccb/dev/fug/comm.py
hvl_ccb/dev/fug/constants.py
hvl_ccb/dev/fug/errors.py
hvl_ccb/dev/fug/fug.py
hvl_ccb/dev/fug/registers.py
hvl_ccb/dev/heinzinger/__init__.py
hvl_ccb/dev/heinzinger/base.py
hvl_ccb/dev/heinzinger/constants.py
hvl_ccb/dev/heinzinger/device.py
hvl_ccb/dev/heinzinger/mixin.py
hvl_ccb/dev/highland_t560/__init__.py
hvl_ccb/dev/highland_t560/base.py
hvl_ccb/dev/highland_t560/channel.py
hvl_ccb/dev/highland_t560/device.py
hvl_ccb/dev/ka3000p/__init__.py
hvl_ccb/dev/ka3000p/base.py
hvl_ccb/dev/ka3000p/comm.py
hvl_ccb/dev/ka3000p/device.py
hvl_ccb/dev/labjack/__init__.py
hvl_ccb/dev/labjack/labjack.py
hvl_ccb/dev/lauda/__init__.py
hvl_ccb/dev/lauda/lauda.py
hvl_ccb/dev/mbw973/__init__.py
hvl_ccb/dev/mbw973/mbw973.py
hvl_ccb/dev/newport/__init__.py
hvl_ccb/dev/newport/newport.py
hvl_ccb/dev/pfa2_filter/__init__.py
hvl_ccb/dev/pfa2_filter/base.py
hvl_ccb/dev/pfa2_filter/device.py
hvl_ccb/dev/pfeiffer_tpg/__init__.py
hvl_ccb/dev/pfeiffer_tpg/pfeiffer_tpg.py
hvl_ccb-0.18.2.dist-info/licenses/AUTHORS.md
hvl_ccb-0.18.2.dist-info/licenses/LICENSE
hvl_ccb-0.18.2.dist-info/METADATA
hvl_ccb-0.18.2.dist-info/WHEEL
hvl_ccb-0.18.2.dist-info/top_level.txt
hvl_ccb-0.18.2.dist-info/RECORD
