Metadata-Version: 2.4
Name: hvl_ccb
Version: 0.18.2
Summary: Python common code base to control research devices, in particular, as used in Christian Franck's High Voltage Lab (HVL), D-ITET, ETH Zurich
Author: Pit Bechtold, Fabian Bill, Alise Chachereau, Maria Del, Joseph Engelbrecht, Raphael Faerber, David Graber, Chi-Ching Hsu, Henning Janssen, Henrik Menne, Luca Nembrini, Mikołaj Rybiński, Ruben Stadler, David Taylor, Hanut Vemulapalli
Maintainer-email: Chi-Ching Hsu <contact-project+ethz-hvl-hvl-ccb-15975897-issue-@incoming.gitlab.com>, Henning Janssen <contact-project+ethz-hvl-hvl-ccb-15975897-issue-@incoming.gitlab.com>
License: GNU General Public License v3
Project-URL: Changelog, https://pypi.org/project/hvl-ccb/#history
Project-URL: Documentation, https://hvl-ccb.readthedocs.io/en/latest/
Project-URL: Homepage, https://gitlab.com/ethz_hvl/hvl_ccb/
Project-URL: Repository, https://gitlab.com/ethz_hvl/hvl_ccb/
Keywords: control,experimenting,high-voltage,instrument,laboratory,research,university
Classifier: Development Status :: 4 - Beta
Classifier: Intended Audience :: Developers
Classifier: Intended Audience :: Education
Classifier: Intended Audience :: Science/Research
Classifier: License :: OSI Approved :: GNU General Public License v3 (GPLv3)
Classifier: Natural Language :: English
Classifier: Programming Language :: Python :: 3.13
Classifier: Programming Language :: Python :: 3.12
Classifier: Programming Language :: Python :: 3.11
Classifier: Programming Language :: Python :: 3.10
Requires-Python: <3.14,>=3.10
License-File: LICENSE
License-File: AUTHORS.md
Requires-Dist: aenum>=3.1.11
Requires-Dist: asyncua>=1.0.1
Requires-Dist: bitstring>=3.1.9
Requires-Dist: numpy>=1.23.4
Requires-Dist: pymodbus>=3.1.1
Requires-Dist: pyserial>=3.5
Requires-Dist: pyvisa-py>=0.5.3
Requires-Dist: pyvisa>=1.12.0
Requires-Dist: typeguard>=3.0.0
Provides-Extra: all
Requires-Dist: hvl_ccb[labjack,picotech,tiepie]; extra == "all"
Provides-Extra: dev
Requires-Dist: build; extra == "dev"
Requires-Dist: coverage>=5.4; extra == "dev"
Requires-Dist: ipdb>=0.13.4; extra == "dev"
Requires-Dist: ipython>=7.19.0; extra == "dev"
Requires-Dist: myst-parser>=4.0; extra == "dev"
Requires-Dist: pip>=21.0; extra == "dev"
Requires-Dist: pre-commit>=2.17; extra == "dev"
Requires-Dist: pytest-cov>=2.11.1; extra == "dev"
Requires-Dist: pytest-env>=1.1.3; extra == "dev"
Requires-Dist: pytest-mock>=3.5.1; extra == "dev"
Requires-Dist: pytest-profiling>=1.8.1; extra == "dev"
Requires-Dist: pytest-xdist>=2.2.0; extra == "dev"
Requires-Dist: sphinx==7.3.7; extra == "dev"
Requires-Dist: sphinx_rtd_theme>=0.5.1; extra == "dev"
Requires-Dist: twine>=3.3.0; extra == "dev"
Requires-Dist: watchdog>=1.0.2; extra == "dev"
Requires-Dist: wheel>=0.36.2; extra == "dev"
Requires-Dist: ruff>=0.12.7; extra == "dev"
Provides-Extra: labjack
Requires-Dist: labjack-ljm>=1.21.0; extra == "labjack"
Provides-Extra: picotech
Requires-Dist: PicoSDK==1.0; extra == "picotech"
Provides-Extra: tiepie
Requires-Dist: python-libtiepie-bi>=1.2.5.1; extra == "tiepie"
Dynamic: license-file
